txtadv/BUILD_DESC.md
txtadv/__init__.py
txtadv/color/__init__.py
txtadv/commands/__init__.py
txtadv/file/__init__.py
txtadv/file/load.py
txtadv/file/save.py
txtadv/location/__init__.py
txtadv/messaging/__init__.py
txtadv/wip/multiplayer/__init__.py
txtadv/wip/multiplayer/recieve.py
txtadv/wip/multiplayer/send.py
txtadv-1.0.dist-info/LICENSE
txtadv-1.0.dist-info/WHEEL
txtadv-1.0.dist-info/METADATA
txtadv-1.0.dist-info/RECORD
