Metadata-Version: 2.1
Name: txtadv
Version: 1.0
Summary: A feature-rich text adventure library! Easy to code in and relativly intuitive, perfect for beginners!
License: MIT
Author: sdft
Author-email: averse.abfun@gmail.com
Requires-Python: >=3.10.0,<3.11
Classifier: License :: OSI Approved :: MIT License
Classifier: Programming Language :: Python :: 3
Classifier: Programming Language :: Python :: 3.10
Provides-Extra: pylint
Requires-Dist: pylint (>=2.17.0,<3.0.0)
